LICENSE
MANIFEST.in
README.rst
setup.cfg
setup.py
src/django_handy_models/__init__.py
src/django_handy_models/admin.py
src/django_handy_models/apps.py
src/django_handy_models/models.py
src/django_handy_models/serializers.py
src/django_handy_models/tests.py
src/django_handy_models/urls.py
src/django_handy_models/views.py
src/django_handy_models.egg-info/PKG-INFO
src/django_handy_models.egg-info/SOURCES.txt
src/django_handy_models.egg-info/dependency_links.txt
src/django_handy_models.egg-info/requires.txt
src/django_handy_models.egg-info/top_level.txt
src/django_handy_models/fixtures/django_handy_models.json
src/django_handy_models/migrations/0001_initial.py
src/django_handy_models/migrations/__init__.py